<?xml version="1.0" encoding="UTF-8" standalone="no"?>
<Configuration>
  <Components>
    <UniqueComponent dnOrder="0" id="aria_gfx_library">
      <Symbols dnOrder="0">
        <Boolean dnOrder="0" id="enableAppSupport">
          <Values dnOrder="0">
            <Dynamic dnOrder="0" id="aria_gfx_library" value="true"/>
          </Values>
        </Boolean>
        <Boolean dnOrder="1" id="enableInput">
          <Values dnOrder="0">
            <User dnOrder="0" value="true"/>
          </Values>
        </Boolean>
        <String dnOrder="2" id="genAriaEventAppHeaderName">
          <Values dnOrder="0">
            <Dynamic dnOrder="0" id="aria_gfx_library" value="app.h"/>
          </Values>
        </String>
        <Boolean dnOrder="3" id="useGlobalPalette">
          <Values dnOrder="0">
            <User dnOrder="0" value="false"/>
          </Values>
        </Boolean>
        <Boolean dnOrder="4" id="useRTOSExtensions">
          <Values dnOrder="0">
            <Dynamic dnOrder="0" id="aria_gfx_library" value="false"/>
          </Values>
        </Boolean>
      </Symbols>
      <Attachments dnOrder="1">
        <DirectDependency dnOrder="0" id="gfx_hal">
          <Attributes dnOrder="0">
            <String dnOrder="0" id="targetComponentID">
              <Value dnOrder="0">gfx_hal</Value>
            </String>
            <String dnOrder="1" id="targetAttachmentID">
              <Value dnOrder="0">gfx_hal</Value>
            </String>
          </Attributes>
        </DirectDependency>
        <GenericDependency dnOrder="1" id="sys_input">
          <Attributes dnOrder="0">
            <Boolean dnOrder="0" id="enabled">
              <Value dnOrder="0">true</Value>
            </Boolean>
          </Attributes>
        </GenericDependency>
      </Attachments>
    </UniqueComponent>
    <UniqueComponent dnOrder="1" id="aria_gfx_xplained_pro">
      <Symbols dnOrder="0">
        <Combo dnOrder="0" id="DisplayInterface">
          <Values dnOrder="0">
            <User dnOrder="0" value="SPI 4-line"/>
          </Values>
        </Combo>
        <Combo dnOrder="1" id="currDisplayInterface">
          <Values dnOrder="0">
            <Dynamic dnOrder="0" id="aria_gfx_xplained_pro" value="SPI 4-line"/>
          </Values>
        </Combo>
      </Symbols>
    </UniqueComponent>
    <UniqueComponent bsp="true" dnOrder="2" id="BSP_PIC32MZ_EF_Curiosity_2.0"/>
    <UniqueComponent dnOrder="3" id="core">
      <Symbols dnOrder="0">
        <String dnOrder="0" id="BSP_PIN_100_MODE">
          <Values dnOrder="0">
            <User dnOrder="0" value="DIGITAL"/>
          </Values>
        </String>
        <String dnOrder="1" id="BSP_PIN_101_MODE">
          <Values dnOrder="0">
            <User dnOrder="0" value="DIGITAL"/>
          </Values>
        </String>
        <String dnOrder="2" id="BSP_PIN_102_MODE">
          <Values dnOrder="0">
            <User dnOrder="0" value="DIGITAL"/>
          </Values>
        </String>
        <String dnOrder="3" id="BSP_PIN_103_MODE">
          <Values dnOrder="0">
            <User dnOrder="0" value="DIGITAL"/>
          </Values>
        </String>
        <String dnOrder="4" id="BSP_PIN_104_FUNCTION_TYPE">
          <Values dnOrder="0">
            <Dynamic dnOrder="0" id="aria_gfx_xplained_pro" value="Available"/>
            <User dnOrder="1" value=""/>
          </Values>
        </String>
        <String dnOrder="5" id="BSP_PIN_104_MODE">
          <Values dnOrder="0">
            <User dnOrder="0" value="DIGITAL"/>
          </Values>
        </String>
        <String dnOrder="6" id="BSP_PIN_106_FUNCTION_TYPE">
          <Values dnOrder="0">
            <Dynamic dnOrder="0" id="aria_gfx_xplained_pro" value="Available"/>
            <User dnOrder="1" value=""/>
          </Values>
        </String>
        <String dnOrder="7" id="BSP_PIN_109_MODE">
          <Values dnOrder="0">
            <User dnOrder="0" value="DIGITAL"/>
          </Values>
        </String>
        <String dnOrder="8" id="BSP_PIN_10_MODE">
          <Values dnOrder="0">
            <User dnOrder="0" value="DIGITAL"/>
          </Values>
        </String>
        <String dnOrder="9" id="BSP_PIN_110_MODE">
          <Values dnOrder="0">
            <User dnOrder="0" value="DIGITAL"/>
          </Values>
        </String>
        <String dnOrder="10" id="BSP_PIN_111_MODE">
          <Values dnOrder="0">
            <User dnOrder="0" value="DIGITAL"/>
          </Values>
        </String>
        <String dnOrder="11" id="BSP_PIN_112_MODE">
          <Values dnOrder="0">
            <User dnOrder="0" value="DIGITAL"/>
          </Values>
        </String>
        <String dnOrder="12" id="BSP_PIN_113_MODE">
          <Values dnOrder="0">
            <User dnOrder="0" value="DIGITAL"/>
          </Values>
        </String>
        <String dnOrder="13" id="BSP_PIN_114_MODE">
          <Values dnOrder="0">
            <User dnOrder="0" value="DIGITAL"/>
          </Values>
        </String>
        <String dnOrder="14" id="BSP_PIN_115_MODE">
          <Values dnOrder="0">
            <User dnOrder="0" value="DIGITAL"/>
          </Values>
        </String>
        <String dnOrder="15" id="BSP_PIN_116_MODE">
          <Values dnOrder="0">
            <User dnOrder="0" value="DIGITAL"/>
          </Values>
        </String>
        <String dnOrder="16" id="BSP_PIN_117_DIR">
          <Values dnOrder="0">
            <User dnOrder="0" value="Out"/>
          </Values>
        </String>
        <String dnOrder="17" id="BSP_PIN_117_LAT">
          <Values dnOrder="0">
            <User dnOrder="0" value="High"/>
          </Values>
        </String>
        <String dnOrder="18" id="BSP_PIN_117_MODE">
          <Values dnOrder="0">
            <User dnOrder="0" value="DIGITAL"/>
          </Values>
        </String>
        <String dnOrder="19" id="BSP_PIN_117_OD">
          <Values dnOrder="0">
            <User dnOrder="0" value="True"/>
          </Values>
        </String>
        <String dnOrder="20" id="BSP_PIN_118_MODE">
          <Values dnOrder="0">
            <User dnOrder="0" value="DIGITAL"/>
          </Values>
        </String>
        <String dnOrder="21" id="BSP_PIN_119_MODE">
          <Values dnOrder="0">
            <User dnOrder="0" value="DIGITAL"/>
          </Values>
        </String>
        <String dnOrder="22" id="BSP_PIN_120_MODE">
          <Values dnOrder="0">
            <User dnOrder="0" value="DIGITAL"/>
          </Values>
        </String>
        <String dnOrder="23" id="BSP_PIN_121_MODE">
          <Values dnOrder="0">
            <User dnOrder="0" value="DIGITAL"/>
          </Values>
        </String>
        <String dnOrder="24" id="BSP_PIN_124_MODE">
          <Values dnOrder="0">
            <User dnOrder="0" value="DIGITAL"/>
          </Values>
        </String>
        <String dnOrder="25" id="BSP_PIN_125_MODE">
          <Values dnOrder="0">
            <User dnOrder="0" value="DIGITAL"/>
          </Values>
        </String>
        <String dnOrder="26" id="BSP_PIN_126_DIR">
          <Values dnOrder="0">
            <User dnOrder="0" value="Out"/>
          </Values>
        </String>
        <String dnOrder="27" id="BSP_PIN_126_LAT">
          <Values dnOrder="0">
            <User dnOrder="0" value="High"/>
          </Values>
        </String>
        <String dnOrder="28" id="BSP_PIN_126_MODE">
          <Values dnOrder="0">
            <User dnOrder="0" value="DIGITAL"/>
          </Values>
        </String>
        <String dnOrder="29" id="BSP_PIN_126_OD">
          <Values dnOrder="0">
            <User dnOrder="0" value="True"/>
          </Values>
        </String>
        <String dnOrder="30" id="BSP_PIN_127_MODE">
          <Values dnOrder="0">
            <User dnOrder="0" value="DIGITAL"/>
          </Values>
        </String>
        <String dnOrder="31" id="BSP_PIN_128_MODE">
          <Values dnOrder="0">
            <User dnOrder="0" value="DIGITAL"/>
          </Values>
        </String>
        <String dnOrder="32" id="BSP_PIN_129_MODE">
          <Values dnOrder="0">
            <User dnOrder="0" value="DIGITAL"/>
          </Values>
        </String>
        <String dnOrder="33" id="BSP_PIN_12_FUNCTION_TYPE">
          <Values dnOrder="0">
            <Dynamic dnOrder="0" id="aria_gfx_xplained_pro" value="Available"/>
            <User dnOrder="1" value=""/>
          </Values>
        </String>
        <String dnOrder="34" id="BSP_PIN_130_MODE">
          <Values dnOrder="0">
            <User dnOrder="0" value="DIGITAL"/>
          </Values>
        </String>
        <String dnOrder="35" id="BSP_PIN_131_MODE">
          <Values dnOrder="0">
            <User dnOrder="0" value="DIGITAL"/>
          </Values>
        </String>
        <String dnOrder="36" id="BSP_PIN_132_MODE">
          <Values dnOrder="0">
            <User dnOrder="0" value="DIGITAL"/>
          </Values>
        </String>
        <String dnOrder="37" id="BSP_PIN_133_MODE">
          <Values dnOrder="0">
            <User dnOrder="0" value="DIGITAL"/>
          </Values>
        </String>
        <String dnOrder="38" id="BSP_PIN_134_DIR">
          <Values dnOrder="0">
            <User dnOrder="0" value="Out"/>
          </Values>
        </String>
        <String dnOrder="39" id="BSP_PIN_134_LAT">
          <Values dnOrder="0">
            <User dnOrder="0" value="High"/>
          </Values>
        </String>
        <String dnOrder="40" id="BSP_PIN_134_MODE">
          <Values dnOrder="0">
            <User dnOrder="0" value="DIGITAL"/>
          </Values>
        </String>
        <String dnOrder="41" id="BSP_PIN_134_OD">
          <Values dnOrder="0">
            <User dnOrder="0" value="True"/>
          </Values>
        </String>
        <String dnOrder="42" id="BSP_PIN_135_MODE">
          <Values dnOrder="0">
            <User dnOrder="0" value="DIGITAL"/>
          </Values>
        </String>
        <String dnOrder="43" id="BSP_PIN_138_MODE">
          <Values dnOrder="0">
            <User dnOrder="0" value="DIGITAL"/>
          </Values>
        </String>
        <String dnOrder="44" id="BSP_PIN_139_MODE">
          <Values dnOrder="0">
            <User dnOrder="0" value="DIGITAL"/>
          </Values>
        </String>
        <String dnOrder="45" id="BSP_PIN_140_MODE">
          <Values dnOrder="0">
            <User dnOrder="0" value="DIGITAL"/>
          </Values>
        </String>
        <String dnOrder="46" id="BSP_PIN_141_MODE">
          <Values dnOrder="0">
            <User dnOrder="0" value="DIGITAL"/>
          </Values>
        </String>
        <String dnOrder="47" id="BSP_PIN_142_MODE">
          <Values dnOrder="0">
            <User dnOrder="0" value="DIGITAL"/>
          </Values>
        </String>
        <String dnOrder="48" id="BSP_PIN_143_MODE">
          <Values dnOrder="0">
            <User dnOrder="0" value="DIGITAL"/>
          </Values>
        </String>
        <String dnOrder="49" id="BSP_PIN_19_DIR">
          <Values dnOrder="0">
            <User dnOrder="0" value=""/>
          </Values>
        </String>
        <String dnOrder="50" id="BSP_PIN_19_FUNCTION_NAME">
          <Values dnOrder="0">
            <User dnOrder="0" value="BSP_MAXTOUCH_CHG"/>
          </Values>
        </String>
        <String dnOrder="51" id="BSP_PIN_19_FUNCTION_TYPE">
          <Values dnOrder="0">
            <User dnOrder="0" value="GPIO"/>
          </Values>
        </String>
        <String dnOrder="52" id="BSP_PIN_19_MODE">
          <Values dnOrder="0">
            <User dnOrder="0" value="DIGITAL"/>
          </Values>
        </String>
        <String dnOrder="53" id="BSP_PIN_20_MODE">
          <Values dnOrder="0">
            <User dnOrder="0" value="DIGITAL"/>
          </Values>
        </String>
        <String dnOrder="54" id="BSP_PIN_25_FUNCTION_TYPE">
          <Values dnOrder="0">
            <Dynamic dnOrder="0" id="aria_gfx_xplained_pro" value="SDI3"/>
          </Values>
        </String>
        <String dnOrder="55" id="BSP_PIN_25_MODE">
          <Values dnOrder="0">
            <User dnOrder="0" value="DIGITAL"/>
          </Values>
        </String>
        <String dnOrder="56" id="BSP_PIN_28_MODE">
          <Values dnOrder="0">
            <User dnOrder="0" value="DIGITAL"/>
          </Values>
        </String>
        <String dnOrder="57" id="BSP_PIN_29_FUNCTION_TYPE">
          <Values dnOrder="0">
            <Dynamic dnOrder="0" id="aria_gfx_xplained_pro" value="Available"/>
            <User dnOrder="1" value=""/>
          </Values>
        </String>
        <String dnOrder="58" id="BSP_PIN_29_MODE">
          <Values dnOrder="0">
            <User dnOrder="0" value="DIGITAL"/>
          </Values>
        </String>
        <String dnOrder="59" id="BSP_PIN_30_MODE">
          <Values dnOrder="0">
            <User dnOrder="0" value="DIGITAL"/>
          </Values>
        </String>
        <String dnOrder="60" id="BSP_PIN_31_FUNCTION_TYPE">
          <Values dnOrder="0">
            <Dynamic dnOrder="0" id="aria_gfx_xplained_pro" value="SDO3"/>
          </Values>
        </String>
        <String dnOrder="61" id="BSP_PIN_31_MODE">
          <Values dnOrder="0">
            <User dnOrder="0" value="DIGITAL"/>
          </Values>
        </String>
        <String dnOrder="62" id="BSP_PIN_34_DIR">
          <Values dnOrder="0">
            <Dynamic dnOrder="0" id="aria_gfx_xplained_pro" value="Out"/>
          </Values>
        </String>
        <String dnOrder="63" id="BSP_PIN_34_FUNCTION_NAME">
          <Values dnOrder="0">
            <Dynamic dnOrder="0" id="aria_gfx_xplained_pro" value="GFX_DISP_INTF_PIN_BACKLIGHT"/>
          </Values>
        </String>
        <String dnOrder="64" id="BSP_PIN_34_FUNCTION_TYPE">
          <Values dnOrder="0">
            <Dynamic dnOrder="0" id="aria_gfx_xplained_pro" value="GPIO"/>
          </Values>
        </String>
        <String dnOrder="65" id="BSP_PIN_34_LAT">
          <Values dnOrder="0">
            <Dynamic dnOrder="0" id="aria_gfx_xplained_pro" value="Low"/>
          </Values>
        </String>
        <String dnOrder="66" id="BSP_PIN_34_MODE">
          <Values dnOrder="0">
            <User dnOrder="0" value="DIGITAL"/>
          </Values>
        </String>
        <String dnOrder="67" id="BSP_PIN_37_FUNCTION_TYPE">
          <Values dnOrder="0">
            <Dynamic dnOrder="0" id="aria_gfx_xplained_pro" value="Available"/>
            <User dnOrder="1" value=""/>
          </Values>
        </String>
        <String dnOrder="68" id="BSP_PIN_38_DIR">
          <Values dnOrder="0">
            <User dnOrder="0" value="Out"/>
          </Values>
        </String>
        <String dnOrder="69" id="BSP_PIN_38_LAT">
          <Values dnOrder="0">
            <User dnOrder="0" value="High"/>
          </Values>
        </String>
        <String dnOrder="70" id="BSP_PIN_38_MODE">
          <Values dnOrder="0">
            <User dnOrder="0" value="DIGITAL"/>
          </Values>
        </String>
        <String dnOrder="71" id="BSP_PIN_38_OD">
          <Values dnOrder="0">
            <User dnOrder="0" value="True"/>
          </Values>
        </String>
        <String dnOrder="72" id="BSP_PIN_45_MODE">
          <Values dnOrder="0">
            <User dnOrder="0" value="DIGITAL"/>
          </Values>
        </String>
        <String dnOrder="73" id="BSP_PIN_46_MODE">
          <Values dnOrder="0">
            <User dnOrder="0" value="DIGITAL"/>
          </Values>
        </String>
        <String dnOrder="74" id="BSP_PIN_47_DIR">
          <Values dnOrder="0">
            <User dnOrder="0" value="Out"/>
          </Values>
        </String>
        <String dnOrder="75" id="BSP_PIN_47_LAT">
          <Values dnOrder="0">
            <User dnOrder="0" value="High"/>
          </Values>
        </String>
        <String dnOrder="76" id="BSP_PIN_47_MODE">
          <Values dnOrder="0">
            <User dnOrder="0" value="DIGITAL"/>
          </Values>
        </String>
        <String dnOrder="77" id="BSP_PIN_47_OD">
          <Values dnOrder="0">
            <User dnOrder="0" value="True"/>
          </Values>
        </String>
        <String dnOrder="78" id="BSP_PIN_48_DIR">
          <Values dnOrder="0">
            <User dnOrder="0" value="Out"/>
          </Values>
        </String>
        <String dnOrder="79" id="BSP_PIN_48_LAT">
          <Values dnOrder="0">
            <User dnOrder="0" value="High"/>
          </Values>
        </String>
        <String dnOrder="80" id="BSP_PIN_48_MODE">
          <Values dnOrder="0">
            <User dnOrder="0" value="DIGITAL"/>
          </Values>
        </String>
        <String dnOrder="81" id="BSP_PIN_48_OD">
          <Values dnOrder="0">
            <User dnOrder="0" value="True"/>
          </Values>
        </String>
        <String dnOrder="82" id="BSP_PIN_51_FUNCTION_TYPE">
          <Values dnOrder="0">
            <Dynamic dnOrder="0" id="aria_gfx_xplained_pro" value="Available"/>
            <User dnOrder="1" value=""/>
          </Values>
        </String>
        <String dnOrder="83" id="BSP_PIN_51_MODE">
          <Values dnOrder="0">
            <User dnOrder="0" value="DIGITAL"/>
          </Values>
        </String>
        <String dnOrder="84" id="BSP_PIN_52_FUNCTION_TYPE">
          <Values dnOrder="0">
            <Dynamic dnOrder="0" id="aria_gfx_xplained_pro" value="Available"/>
            <User dnOrder="1" value=""/>
          </Values>
        </String>
        <String dnOrder="85" id="BSP_PIN_52_MODE">
          <Values dnOrder="0">
            <User dnOrder="0" value="DIGITAL"/>
          </Values>
        </String>
        <String dnOrder="86" id="BSP_PIN_53_FUNCTION_TYPE">
          <Values dnOrder="0">
            <Dynamic dnOrder="0" id="aria_gfx_xplained_pro" value="Available"/>
            <User dnOrder="1" value=""/>
          </Values>
        </String>
        <String dnOrder="87" id="BSP_PIN_53_MODE">
          <Values dnOrder="0">
            <User dnOrder="0" value="DIGITAL"/>
          </Values>
        </String>
        <String dnOrder="88" id="BSP_PIN_57_FUNCTION_TYPE">
          <Values dnOrder="0">
            <Dynamic dnOrder="0" id="aria_gfx_xplained_pro" value="Available"/>
            <User dnOrder="1" value=""/>
          </Values>
        </String>
        <String dnOrder="89" id="BSP_PIN_61_FUNCTION_TYPE">
          <Values dnOrder="0">
            <Dynamic dnOrder="0" id="aria_gfx_xplained_pro" value="SCK3"/>
          </Values>
        </String>
        <String dnOrder="90" id="BSP_PIN_61_MODE">
          <Values dnOrder="0">
            <User dnOrder="0" value="DIGITAL"/>
          </Values>
        </String>
        <String dnOrder="91" id="BSP_PIN_62_DIR">
          <Values dnOrder="0">
            <Dynamic dnOrder="0" id="aria_gfx_xplained_pro" value="Out"/>
          </Values>
        </String>
        <String dnOrder="92" id="BSP_PIN_62_FUNCTION_NAME">
          <Values dnOrder="0">
            <Dynamic dnOrder="0" id="aria_gfx_xplained_pro" value="GFX_DISP_INTF_PIN_CS"/>
          </Values>
        </String>
        <String dnOrder="93" id="BSP_PIN_62_FUNCTION_TYPE">
          <Values dnOrder="0">
            <Dynamic dnOrder="0" id="aria_gfx_xplained_pro" value="GPIO"/>
          </Values>
        </String>
        <String dnOrder="94" id="BSP_PIN_62_LAT">
          <Values dnOrder="0">
            <Dynamic dnOrder="0" id="aria_gfx_xplained_pro" value="High"/>
          </Values>
        </String>
        <String dnOrder="95" id="BSP_PIN_62_MODE">
          <Values dnOrder="0">
            <User dnOrder="0" value="DIGITAL"/>
          </Values>
        </String>
        <String dnOrder="96" id="BSP_PIN_68_MODE">
          <Values dnOrder="0">
            <User dnOrder="0" value="DIGITAL"/>
          </Values>
        </String>
        <String dnOrder="97" id="BSP_PIN_72_MODE">
          <Values dnOrder="0">
            <User dnOrder="0" value="DIGITAL"/>
          </Values>
        </String>
        <String dnOrder="98" id="BSP_PIN_73_MODE">
          <Values dnOrder="0">
            <User dnOrder="0" value="DIGITAL"/>
          </Values>
        </String>
        <String dnOrder="99" id="BSP_PIN_78_MODE">
          <Values dnOrder="0">
            <User dnOrder="0" value="DIGITAL"/>
          </Values>
        </String>
        <String dnOrder="100" id="BSP_PIN_79_MODE">
          <Values dnOrder="0">
            <User dnOrder="0" value="DIGITAL"/>
          </Values>
        </String>
        <String dnOrder="101" id="BSP_PIN_80_MODE">
          <Values dnOrder="0">
            <User dnOrder="0" value="DIGITAL"/>
          </Values>
        </String>
        <String dnOrder="102" id="BSP_PIN_81_MODE">
          <Values dnOrder="0">
            <User dnOrder="0" value="DIGITAL"/>
          </Values>
        </String>
        <String dnOrder="103" id="BSP_PIN_82_MODE">
          <Values dnOrder="0">
            <User dnOrder="0" value="DIGITAL"/>
          </Values>
        </String>
        <String dnOrder="104" id="BSP_PIN_83_MODE">
          <Values dnOrder="0">
            <User dnOrder="0" value="DIGITAL"/>
          </Values>
        </String>
        <String dnOrder="105" id="BSP_PIN_84_MODE">
          <Values dnOrder="0">
            <User dnOrder="0" value="DIGITAL"/>
          </Values>
        </String>
        <String dnOrder="106" id="BSP_PIN_85_MODE">
          <Values dnOrder="0">
            <User dnOrder="0" value="DIGITAL"/>
          </Values>
        </String>
        <String dnOrder="107" id="BSP_PIN_86_MODE">
          <Values dnOrder="0">
            <User dnOrder="0" value="DIGITAL"/>
          </Values>
        </String>
        <String dnOrder="108" id="BSP_PIN_87_MODE">
          <Values dnOrder="0">
            <User dnOrder="0" value="DIGITAL"/>
          </Values>
        </String>
        <String dnOrder="109" id="BSP_PIN_90_MODE">
          <Values dnOrder="0">
            <User dnOrder="0" value="DIGITAL"/>
          </Values>
        </String>
        <String dnOrder="110" id="BSP_PIN_91_MODE">
          <Values dnOrder="0">
            <User dnOrder="0" value="DIGITAL"/>
          </Values>
        </String>
        <String dnOrder="111" id="BSP_PIN_92_DIR">
          <Values dnOrder="0">
            <Dynamic dnOrder="0" id="aria_gfx_xplained_pro" value="Out"/>
          </Values>
        </String>
        <String dnOrder="112" id="BSP_PIN_92_FUNCTION_NAME">
          <Values dnOrder="0">
            <Dynamic dnOrder="0" id="aria_gfx_xplained_pro" value="GFX_DISP_INTF_PIN_RSDC"/>
          </Values>
        </String>
        <String dnOrder="113" id="BSP_PIN_92_FUNCTION_TYPE">
          <Values dnOrder="0">
            <Dynamic dnOrder="0" id="aria_gfx_xplained_pro" value="GPIO"/>
          </Values>
        </String>
        <String dnOrder="114" id="BSP_PIN_92_LAT">
          <Values dnOrder="0">
            <Dynamic dnOrder="0" id="aria_gfx_xplained_pro" value="High"/>
          </Values>
        </String>
        <String dnOrder="115" id="BSP_PIN_92_MODE">
          <Values dnOrder="0">
            <User dnOrder="0" value="DIGITAL"/>
          </Values>
        </String>
        <String dnOrder="116" id="BSP_PIN_93_MODE">
          <Values dnOrder="0">
            <User dnOrder="0" value="DIGITAL"/>
          </Values>
        </String>
        <String dnOrder="117" id="BSP_PIN_94_DIR">
          <Values dnOrder="0">
            <Dynamic dnOrder="0" id="aria_gfx_xplained_pro" value="Out"/>
          </Values>
        </String>
        <String dnOrder="118" id="BSP_PIN_94_FUNCTION_NAME">
          <Values dnOrder="0">
            <Dynamic dnOrder="0" id="aria_gfx_xplained_pro" value="GFX_DISP_INTF_PIN_RESET"/>
          </Values>
        </String>
        <String dnOrder="119" id="BSP_PIN_94_FUNCTION_TYPE">
          <Values dnOrder="0">
            <Dynamic dnOrder="0" id="aria_gfx_xplained_pro" value="GPIO"/>
          </Values>
        </String>
        <String dnOrder="120" id="BSP_PIN_94_LAT">
          <Values dnOrder="0">
            <Dynamic dnOrder="0" id="aria_gfx_xplained_pro" value="Low"/>
          </Values>
        </String>
        <String dnOrder="121" id="BSP_PIN_94_MODE">
          <Values dnOrder="0">
            <User dnOrder="0" value="DIGITAL"/>
          </Values>
        </String>
        <String dnOrder="122" id="BSP_PIN_95_FUNCTION_TYPE">
          <Values dnOrder="0">
            <User dnOrder="0" value="SCL1"/>
          </Values>
        </String>
        <String dnOrder="123" id="BSP_PIN_95_MODE">
          <Values dnOrder="0">
            <User dnOrder="0" value="DIGITAL"/>
          </Values>
        </String>
        <String dnOrder="124" id="BSP_PIN_95_PU">
          <Values dnOrder="0">
            <User dnOrder="0" value=""/>
          </Values>
        </String>
        <String dnOrder="125" id="BSP_PIN_96_FUNCTION_TYPE">
          <Values dnOrder="0">
            <User dnOrder="0" value="SDA1"/>
          </Values>
        </String>
        <String dnOrder="126" id="BSP_PIN_96_MODE">
          <Values dnOrder="0">
            <User dnOrder="0" value="DIGITAL"/>
          </Values>
        </String>
        <String dnOrder="127" id="BSP_PIN_96_PU">
          <Values dnOrder="0">
            <User dnOrder="0" value=""/>
          </Values>
        </String>
        <String dnOrder="128" id="BSP_PIN_97_MODE">
          <Values dnOrder="0">
            <User dnOrder="0" value="DIGITAL"/>
          </Values>
        </String>
        <String dnOrder="129" id="BSP_PIN_98_MODE">
          <Values dnOrder="0">
            <User dnOrder="0" value="DIGITAL"/>
          </Values>
        </String>
        <String dnOrder="130" id="BSP_PIN_99_MODE">
          <Values dnOrder="0">
            <User dnOrder="0" value="DIGITAL"/>
          </Values>
        </String>
        <String dnOrder="131" id="BSP_PIN_9_MODE">
          <Values dnOrder="0">
            <User dnOrder="0" value="DIGITAL"/>
          </Values>
        </String>
        <KeyValueSet dnOrder="132" id="COMPILER_CHOICE">
          <Values dnOrder="0">
            <Dynamic dnOrder="0" id="core" value="0"/>
          </Values>
        </KeyValueSet>
        <Boolean dnOrder="133" id="CORE_SOFTWARE_0_INTERRUPT_ENABLE_UPDATE">
          <Values dnOrder="0">
            <Dynamic dnOrder="0" id="core" value="true"/>
          </Values>
        </Boolean>
        <Boolean dnOrder="134" id="CORE_TIMER_INTERRUPT_ENABLE">
          <Values dnOrder="0">
            <Dynamic dnOrder="0" id="core_timer" value="true"/>
          </Values>
        </Boolean>
        <Boolean dnOrder="135" id="CORE_TIMER_INTERRUPT_ENABLE_UPDATE">
          <Values dnOrder="0">
            <Dynamic dnOrder="0" id="core" value="false"/>
          </Values>
        </Boolean>
        <String dnOrder="136" id="CORE_TIMER_INTERRUPT_HANDLER">
          <Values dnOrder="0">
            <Dynamic dnOrder="0" id="core_timer" value="CORE_TIMER_InterruptHandler"/>
          </Values>
        </String>
        <Boolean dnOrder="137" id="CORE_TIMER_INTERRUPT_HANDLER_LOCK">
          <Values dnOrder="0">
            <Dynamic dnOrder="0" id="core_timer" value="true"/>
          </Values>
        </Boolean>
        <Boolean dnOrder="138" id="DMA_CH_NEEDED_FOR_SPI3_Receive">
          <Values dnOrder="0">
            <Dynamic dnOrder="0" id="drv_spi_0" value="false"/>
          </Values>
        </Boolean>
        <Boolean dnOrder="139" id="DMA_CH_NEEDED_FOR_SPI3_Transmit">
          <Values dnOrder="0">
            <Dynamic dnOrder="0" id="drv_spi_0" value="false"/>
          </Values>
        </Boolean>
        <Integer dnOrder="140" id="EBI_CLOCK_FREQUENCY">
          <Values dnOrder="0">
            <Dynamic dnOrder="0" id="core" value="0"/>
          </Values>
        </Integer>
        <Boolean dnOrder="141" id="EVIC_0_ENABLE">
          <Values dnOrder="0">
            <Dynamic dnOrder="0" id="core" value="true"/>
          </Values>
        </Boolean>
        <Boolean dnOrder="142" id="EVIC_0_HANDLER_LOCK">
          <Values dnOrder="0">
            <Dynamic dnOrder="0" id="core" value="true"/>
          </Values>
        </Boolean>
        <String dnOrder="143" id="EVIC_0_INTERRUPT_HANDLER">
          <Values dnOrder="0">
            <Dynamic dnOrder="0" id="core" value="CORE_TIMER_InterruptHandler"/>
          </Values>
        </String>
        <Boolean dnOrder="144" id="EVIC_115_ENABLE">
          <Values dnOrder="0">
            <Dynamic dnOrder="0" id="core" value="true"/>
          </Values>
        </Boolean>
        <Boolean dnOrder="145" id="EVIC_115_HANDLER_LOCK">
          <Values dnOrder="0">
            <Dynamic dnOrder="0" id="core" value="true"/>
          </Values>
        </Boolean>
        <String dnOrder="146" id="EVIC_115_INTERRUPT_HANDLER">
          <Values dnOrder="0">
            <Dynamic dnOrder="0" id="core" value="I2C1_BUS_InterruptHandler"/>
          </Values>
        </String>
        <Boolean dnOrder="147" id="EVIC_117_ENABLE">
          <Values dnOrder="0">
            <Dynamic dnOrder="0" id="core" value="true"/>
          </Values>
        </Boolean>
        <Boolean dnOrder="148" id="EVIC_117_HANDLER_LOCK">
          <Values dnOrder="0">
            <Dynamic dnOrder="0" id="core" value="true"/>
          </Values>
        </Boolean>
        <String dnOrder="149" id="EVIC_117_INTERRUPT_HANDLER">
          <Values dnOrder="0">
            <Dynamic dnOrder="0" id="core" value="I2C1_MASTER_InterruptHandler"/>
          </Values>
        </String>
        <Boolean dnOrder="150" id="EVIC_148_ENABLE">
          <Values dnOrder="0">
            <Dynamic dnOrder="0" id="core" value="false"/>
          </Values>
        </Boolean>
        <Boolean dnOrder="151" id="EVIC_148_HANDLER_LOCK">
          <Values dnOrder="0">
            <Dynamic dnOrder="0" id="core" value="false"/>
          </Values>
        </Boolean>
        <String dnOrder="152" id="EVIC_148_INTERRUPT_HANDLER">
          <Values dnOrder="0">
            <Dynamic dnOrder="0" id="core" value="I2C2_BUS_Handler"/>
          </Values>
        </String>
        <Boolean dnOrder="153" id="EVIC_150_ENABLE">
          <Values dnOrder="0">
            <Dynamic dnOrder="0" id="core" value="false"/>
          </Values>
        </Boolean>
        <Boolean dnOrder="154" id="EVIC_150_HANDLER_LOCK">
          <Values dnOrder="0">
            <Dynamic dnOrder="0" id="core" value="false"/>
          </Values>
        </Boolean>
        <String dnOrder="155" id="EVIC_150_INTERRUPT_HANDLER">
          <Values dnOrder="0">
            <Dynamic dnOrder="0" id="core" value="I2C2_MASTER_Handler"/>
          </Values>
        </String>
        <Boolean dnOrder="156" id="EVIC_155_ENABLE">
          <Values dnOrder="0">
            <Dynamic dnOrder="0" id="core" value="true"/>
          </Values>
        </Boolean>
        <Boolean dnOrder="157" id="EVIC_155_HANDLER_LOCK">
          <Values dnOrder="0">
            <Dynamic dnOrder="0" id="core" value="true"/>
          </Values>
        </Boolean>
        <String dnOrder="158" id="EVIC_155_INTERRUPT_HANDLER">
          <Values dnOrder="0">
            <Dynamic dnOrder="0" id="core" value="SPI3_RX_InterruptHandler"/>
          </Values>
        </String>
        <Boolean dnOrder="159" id="EVIC_156_ENABLE">
          <Values dnOrder="0">
            <Dynamic dnOrder="0" id="core" value="true"/>
          </Values>
        </Boolean>
        <Boolean dnOrder="160" id="EVIC_156_HANDLER_LOCK">
          <Values dnOrder="0">
            <Dynamic dnOrder="0" id="core" value="true"/>
          </Values>
        </Boolean>
        <String dnOrder="161" id="EVIC_156_INTERRUPT_HANDLER">
          <Values dnOrder="0">
            <Dynamic dnOrder="0" id="core" value="SPI3_TX_InterruptHandler"/>
          </Values>
        </String>
        <Boolean dnOrder="162" id="EVIC_1_ENABLE">
          <Values dnOrder="0">
            <Dynamic dnOrder="0" id="core" value="false"/>
          </Values>
        </Boolean>
        <Boolean dnOrder="163" id="EVIC_1_ENABLE_GENERATE">
          <Values dnOrder="0">
            <Dynamic dnOrder="0" id="core" value="true"/>
          </Values>
        </Boolean>
        <Boolean dnOrder="164" id="EVIC_1_ENABLE_LOCK">
          <Values dnOrder="0">
            <Dynamic dnOrder="0" id="core" value="false"/>
          </Values>
        </Boolean>
        <Boolean dnOrder="165" id="EVIC_1_HANDLER_LOCK">
          <Values dnOrder="0">
            <Dynamic dnOrder="0" id="core" value="false"/>
          </Values>
        </Boolean>
        <Boolean dnOrder="166" id="EVIC_1_PRIORITY_GENERATE">
          <Values dnOrder="0">
            <Dynamic dnOrder="0" id="core" value="true"/>
          </Values>
        </Boolean>
        <Boolean dnOrder="167" id="EVIC_1_PRIORITY_LOCK">
          <Values dnOrder="0">
            <Dynamic dnOrder="0" id="core" value="false"/>
          </Values>
        </Boolean>
        <Boolean dnOrder="168" id="EVIC_1_SUBPRIORITY_GENERATE">
          <Values dnOrder="0">
            <Dynamic dnOrder="0" id="core" value="true"/>
          </Values>
        </Boolean>
        <Boolean dnOrder="169" id="EVIC_1_SUBPRIORITY_LOCK">
          <Values dnOrder="0">
            <Dynamic dnOrder="0" id="core" value="false"/>
          </Values>
        </Boolean>
        <Boolean dnOrder="170" id="EVIC_4_ENABLE_GENERATE">
          <Values dnOrder="0">
            <Dynamic dnOrder="0" id="core" value="true"/>
          </Values>
        </Boolean>
        <Boolean dnOrder="171" id="EVIC_4_ENABLE_LOCK">
          <Values dnOrder="0">
            <Dynamic dnOrder="0" id="core" value="false"/>
          </Values>
        </Boolean>
        <Boolean dnOrder="172" id="EVIC_4_HANDLER_LOCK">
          <Values dnOrder="0">
            <Dynamic dnOrder="0" id="core" value="false"/>
          </Values>
        </Boolean>
        <Boolean dnOrder="173" id="EVIC_4_PRIORITY_GENERATE">
          <Values dnOrder="0">
            <Dynamic dnOrder="0" id="core" value="true"/>
          </Values>
        </Boolean>
        <Boolean dnOrder="174" id="EVIC_4_PRIORITY_LOCK">
          <Values dnOrder="0">
            <Dynamic dnOrder="0" id="core" value="false"/>
          </Values>
        </Boolean>
        <Boolean dnOrder="175" id="EVIC_4_SUBPRIORITY_GENERATE">
          <Values dnOrder="0">
            <Dynamic dnOrder="0" id="core" value="true"/>
          </Values>
        </Boolean>
        <Boolean dnOrder="176" id="EVIC_4_SUBPRIORITY_LOCK">
          <Values dnOrder="0">
            <Dynamic dnOrder="0" id="core" value="false"/>
          </Values>
        </Boolean>
        <Boolean dnOrder="177" id="I2C1_BUS_INTERRUPT_ENABLE">
          <Values dnOrder="0">
            <Dynamic dnOrder="0" id="i2c1" value="true"/>
          </Values>
        </Boolean>
        <Boolean dnOrder="178" id="I2C1_BUS_INTERRUPT_ENABLE_UPDATE">
          <Values dnOrder="0">
            <Dynamic dnOrder="0" id="core" value="false"/>
          </Values>
        </Boolean>
        <String dnOrder="179" id="I2C1_BUS_INTERRUPT_HANDLER">
          <Values dnOrder="0">
            <Dynamic dnOrder="0" id="i2c1" value="I2C1_BUS_InterruptHandler"/>
          </Values>
        </String>
        <Boolean dnOrder="180" id="I2C1_BUS_INTERRUPT_HANDLER_LOCK">
          <Values dnOrder="0">
            <Dynamic dnOrder="0" id="i2c1" value="true"/>
          </Values>
        </Boolean>
        <Boolean dnOrder="181" id="I2C1_CLOCK_ENABLE">
          <Values dnOrder="0">
            <Dynamic dnOrder="0" id="i2c1" value="true"/>
          </Values>
        </Boolean>
        <Integer dnOrder="182" id="I2C1_CLOCK_FREQUENCY">
          <Values dnOrder="0">
            <Dynamic dnOrder="0" id="core" value="100000000"/>
          </Values>
        </Integer>
        <Boolean dnOrder="183" id="I2C1_MASTER_INTERRUPT_ENABLE">
          <Values dnOrder="0">
            <Dynamic dnOrder="0" id="i2c1" value="true"/>
          </Values>
        </Boolean>
        <Boolean dnOrder="184" id="I2C1_MASTER_INTERRUPT_ENABLE_UPDATE">
          <Values dnOrder="0">
            <Dynamic dnOrder="0" id="core" value="false"/>
          </Values>
        </Boolean>
        <String dnOrder="185" id="I2C1_MASTER_INTERRUPT_HANDLER">
          <Values dnOrder="0">
            <Dynamic dnOrder="0" id="i2c1" value="I2C1_MASTER_InterruptHandler"/>
          </Values>
        </String>
        <Boolean dnOrder="186" id="I2C1_MASTER_INTERRUPT_HANDLER_LOCK">
          <Values dnOrder="0">
            <Dynamic dnOrder="0" id="i2c1" value="true"/>
          </Values>
        </Boolean>
        <Boolean dnOrder="187" id="I2C2_BUS_INTERRUPT_ENABLE_UPDATE">
          <Values dnOrder="0">
            <Dynamic dnOrder="0" id="core" value="true"/>
          </Values>
        </Boolean>
        <Integer dnOrder="188" id="I2C2_CLOCK_FREQUENCY">
          <Values dnOrder="0">
            <Dynamic dnOrder="0" id="core" value="0"/>
          </Values>
        </Integer>
        <Boolean dnOrder="189" id="I2C2_MASTER_INTERRUPT_ENABLE_UPDATE">
          <Values dnOrder="0">
            <Dynamic dnOrder="0" id="core" value="true"/>
          </Values>
        </Boolean>
        <String dnOrder="190" id="KEIL_STACK_HEAP_SIZE">
          <Values dnOrder="0">
            <Dynamic dnOrder="0" id="core" value="0x1200"/>
          </Values>
        </String>
        <Hex dnOrder="191" id="PMD4_REG_VALUE">
          <Values dnOrder="0">
            <Dynamic dnOrder="0" id="core" value="4294967295"/>
          </Values>
        </Hex>
        <Hex dnOrder="192" id="PMD5_REG_VALUE">
          <Values dnOrder="0">
            <Dynamic dnOrder="0" id="core" value="4278123519"/>
          </Values>
        </Hex>
        <Hex dnOrder="193" id="PMD6_REG_VALUE">
          <Values dnOrder="0">
            <Dynamic dnOrder="0" id="core" value="4294963455"/>
          </Values>
        </Hex>
        <Hex dnOrder="194" id="PMD7_REG_VALUE">
          <Values dnOrder="0">
            <Dynamic dnOrder="0" id="core" value="4294967279"/>
          </Values>
        </Hex>
        <Boolean dnOrder="195" id="SPI3_CLOCK_ENABLE">
          <Values dnOrder="0">
            <Dynamic dnOrder="0" id="spi3" value="true"/>
          </Values>
        </Boolean>
        <Integer dnOrder="196" id="SPI3_CLOCK_FREQUENCY">
          <Values dnOrder="0">
            <Dynamic dnOrder="0" id="core" value="100000000"/>
          </Values>
        </Integer>
        <Boolean dnOrder="197" id="SPI3_RX_INTERRUPT_ENABLE">
          <Values dnOrder="0">
            <Dynamic dnOrder="0" id="spi3" value="true"/>
          </Values>
        </Boolean>
        <Boolean dnOrder="198" id="SPI3_RX_INTERRUPT_ENABLE_UPDATE">
          <Values dnOrder="0">
            <Dynamic dnOrder="0" id="core" value="false"/>
          </Values>
        </Boolean>
        <String dnOrder="199" id="SPI3_RX_INTERRUPT_HANDLER">
          <Values dnOrder="0">
            <Dynamic dnOrder="0" id="spi3" value="SPI3_RX_InterruptHandler"/>
          </Values>
        </String>
        <Boolean dnOrder="200" id="SPI3_RX_INTERRUPT_HANDLER_LOCK">
          <Values dnOrder="0">
            <Dynamic dnOrder="0" id="spi3" value="true"/>
          </Values>
        </Boolean>
        <Boolean dnOrder="201" id="SPI3_TX_INTERRUPT_ENABLE">
          <Values dnOrder="0">
            <Dynamic dnOrder="0" id="spi3" value="true"/>
          </Values>
        </Boolean>
        <Boolean dnOrder="202" id="SPI3_TX_INTERRUPT_ENABLE_UPDATE">
          <Values dnOrder="0">
            <Dynamic dnOrder="0" id="core" value="false"/>
          </Values>
        </Boolean>
        <String dnOrder="203" id="SPI3_TX_INTERRUPT_HANDLER">
          <Values dnOrder="0">
            <Dynamic dnOrder="0" id="spi3" value="SPI3_TX_InterruptHandler"/>
          </Values>
        </String>
        <Boolean dnOrder="204" id="SPI3_TX_INTERRUPT_HANDLER_LOCK">
          <Values dnOrder="0">
            <Dynamic dnOrder="0" id="spi3" value="true"/>
          </Values>
        </Boolean>
        <Hex dnOrder="205" id="SYS_PORT_A_CNPU">
          <Values dnOrder="0">
            <Dynamic dnOrder="0" id="core" value="0"/>
          </Values>
        </Hex>
        <Hex dnOrder="206" id="SYS_PORT_B_ANSEL">
          <Values dnOrder="0">
            <Dynamic dnOrder="0" id="core" value="50092"/>
          </Values>
        </Hex>
        <Hex dnOrder="207" id="SYS_PORT_B_LAT">
          <Values dnOrder="0">
            <Dynamic dnOrder="0" id="core" value="33664"/>
          </Values>
        </Hex>
        <Hex dnOrder="208" id="SYS_PORT_B_ODC">
          <Values dnOrder="0">
            <Dynamic dnOrder="0" id="core" value="896"/>
          </Values>
        </Hex>
        <Hex dnOrder="209" id="SYS_PORT_B_TRIS">
          <Values dnOrder="0">
            <Dynamic dnOrder="0" id="core" value="33668"/>
          </Values>
        </Hex>
        <Hex dnOrder="210" id="SYS_PORT_C_LAT">
          <Values dnOrder="0">
            <Dynamic dnOrder="0" id="core" value="0"/>
          </Values>
        </Hex>
        <Hex dnOrder="211" id="SYS_PORT_C_TRIS">
          <Values dnOrder="0">
            <Dynamic dnOrder="0" id="core" value="0"/>
          </Values>
        </Hex>
        <Hex dnOrder="212" id="SYS_PORT_D_LAT">
          <Values dnOrder="0">
            <Dynamic dnOrder="0" id="core" value="0"/>
          </Values>
        </Hex>
        <Hex dnOrder="213" id="SYS_PORT_D_TRIS">
          <Values dnOrder="0">
            <Dynamic dnOrder="0" id="core" value="0"/>
          </Values>
        </Hex>
        <Hex dnOrder="214" id="SYS_PORT_F_LAT">
          <Values dnOrder="0">
            <Dynamic dnOrder="0" id="core" value="0"/>
          </Values>
        </Hex>
        <Hex dnOrder="215" id="SYS_PORT_F_TRIS">
          <Values dnOrder="0">
            <Dynamic dnOrder="0" id="core" value="0"/>
          </Values>
        </Hex>
        <Hex dnOrder="216" id="SYS_PORT_J_LAT">
          <Values dnOrder="0">
            <Dynamic dnOrder="0" id="core" value="136"/>
          </Values>
        </Hex>
        <Hex dnOrder="217" id="SYS_PORT_J_ODC">
          <Values dnOrder="0">
            <Dynamic dnOrder="0" id="core" value="136"/>
          </Values>
        </Hex>
        <Hex dnOrder="218" id="SYS_PORT_J_TRIS">
          <Values dnOrder="0">
            <Dynamic dnOrder="0" id="core" value="136"/>
          </Values>
        </Hex>
        <Hex dnOrder="219" id="SYS_PORT_K_LAT">
          <Values dnOrder="0">
            <Dynamic dnOrder="0" id="core" value="144"/>
          </Values>
        </Hex>
        <Hex dnOrder="220" id="SYS_PORT_K_ODC">
          <Values dnOrder="0">
            <Dynamic dnOrder="0" id="core" value="128"/>
          </Values>
        </Hex>
        <Hex dnOrder="221" id="SYS_PORT_K_TRIS">
          <Values dnOrder="0">
            <Dynamic dnOrder="0" id="core" value="208"/>
          </Values>
        </Hex>
        <Combo dnOrder="222" id="SYS_PORT_PPS_INPUT_FUNCTION_0">
          <Attributes dnOrder="0">
            <Boolean dnOrder="0" id="visible">
              <Value dnOrder="0">true</Value>
            </Boolean>
          </Attributes>
          <Values dnOrder="1">
            <User dnOrder="0" value="SDI3"/>
          </Values>
        </Combo>
        <KeyValueSet dnOrder="223" id="SYS_PORT_PPS_INPUT_PIN_0">
          <Attributes dnOrder="0">
            <Boolean dnOrder="0" id="visible">
              <Value dnOrder="0">true</Value>
            </Boolean>
          </Attributes>
          <Values dnOrder="1">
            <User dnOrder="0" value="48"/>
          </Values>
        </KeyValueSet>
        <KeyValueSet dnOrder="224" id="SYS_PORT_PPS_OUTPUT_FUNCTION_0">
          <Attributes dnOrder="0">
            <Boolean dnOrder="0" id="visible">
              <Value dnOrder="0">true</Value>
            </Boolean>
          </Attributes>
          <Values dnOrder="1">
            <User dnOrder="0" value="33"/>
          </Values>
        </KeyValueSet>
        <Combo dnOrder="225" id="SYS_PORT_PPS_OUTPUT_PIN_0">
          <Attributes dnOrder="0">
            <Boolean dnOrder="0" id="visible">
              <Value dnOrder="0">true</Value>
            </Boolean>
          </Attributes>
          <Values dnOrder="1">
            <User dnOrder="0" value="RPB3"/>
          </Values>
        </Combo>
        <Boolean dnOrder="226" id="TIMER_1_INTERRUPT_ENABLE_UPDATE">
          <Values dnOrder="0">
            <Dynamic dnOrder="0" id="core" value="true"/>
          </Values>
        </Boolean>
        <Integer dnOrder="227" id="TMR1_CLOCK_FREQUENCY">
          <Values dnOrder="0">
            <Dynamic dnOrder="0" id="core" value="0"/>
          </Values>
        </Integer>
        <Boolean dnOrder="228" id="USE_PPS_INPUT_0">
          <Values dnOrder="0">
            <User dnOrder="0" value="true"/>
          </Values>
        </Boolean>
        <Boolean dnOrder="229" id="USE_PPS_OUTPUT_0">
          <Values dnOrder="0">
            <User dnOrder="0" value="true"/>
          </Values>
        </Boolean>
        <Setting dnOrder="230" id="XC32_HEAP">
          <Attributes dnOrder="0">
            <String dnOrder="0" id="value">
              <Value dnOrder="0">16384</Value>
            </String>
          </Attributes>
        </Setting>
        <Integer dnOrder="231" id="XC32_HEAP_SIZE">
          <Values dnOrder="0">
            <Dynamic dnOrder="0" id="aria_gfx_library" value="16384"/>
          </Values>
        </Integer>
        <KeyValueSet dnOrder="232" id="clkSvcMode">
          <Values dnOrder="0">
            <Dynamic dnOrder="0" id="core" value="0"/>
          </Values>
        </KeyValueSet>
      </Symbols>
    </UniqueComponent>
    <UniqueComponent dnOrder="4" id="core_timer">
      <Symbols dnOrder="0">
        <Integer dnOrder="0" id="CORE_TIMER_FREQUENCY">
          <Values dnOrder="0">
            <Dynamic dnOrder="0" id="core_timer" value="100000000"/>
          </Values>
        </Integer>
        <Boolean dnOrder="1" id="CORE_TIMER_INTERRUPT_MODE">
          <Values dnOrder="0">
            <Dynamic dnOrder="0" id="core_timer" value="true"/>
          </Values>
        </Boolean>
        <Boolean dnOrder="2" id="CORE_TIMER_PERIODIC_INTERRUPT">
          <Attributes dnOrder="0">
            <Boolean dnOrder="0" id="visible">
              <Value dnOrder="0">true</Value>
            </Boolean>
          </Attributes>
          <Values dnOrder="1">
            <Dynamic dnOrder="0" id="core_timer" value="false"/>
          </Values>
        </Boolean>
        <Integer dnOrder="3" id="CORE_TIMER_PERIOD_US">
          <Values dnOrder="0">
            <Dynamic dnOrder="0" id="core_timer" value="1000"/>
          </Values>
        </Integer>
        <String dnOrder="4" id="CORE_TIMER_PERIOD_VALUE">
          <Values dnOrder="0">
            <Dynamic dnOrder="0" id="core_timer" value="0x186a0"/>
          </Values>
        </String>
      </Symbols>
      <Attachments dnOrder="1">
        <DirectCapability dnOrder="0" id="CORE_TIMER_TMR">
          <Attributes dnOrder="0">
            <String dnOrder="0" id="targetComponentID">
              <Value dnOrder="0">sys_time</Value>
            </String>
            <String dnOrder="1" id="targetAttachmentID">
              <Value dnOrder="0">sys_time_TMR_dependency</Value>
            </String>
          </Attributes>
        </DirectCapability>
      </Attachments>
    </UniqueComponent>
    <UniqueComponent dnOrder="5" id="dfp"/>
    <GeneratorComponent dnOrder="6" id="drv_i2c">
      <Symbols dnOrder="0">
        <Combo dnOrder="0" id="DRV_I2C_MODE">
          <Values dnOrder="0">
            <Dynamic dnOrder="0" id="drv_i2c" value="Asynchronous"/>
          </Values>
        </Combo>
      </Symbols>
      <Instances dnOrder="1">
        <InstanceComponent dnOrder="0" id="drv_i2c" instance="0">
          <Symbols dnOrder="0">
            <String dnOrder="0" id="DRV_I2C_PLIB">
              <Values dnOrder="0">
                <Dynamic dnOrder="0" id="drv_i2c_0" value="I2C1"/>
              </Values>
            </String>
          </Symbols>
          <Attachments dnOrder="1">
            <DirectCapability dnOrder="0" id="drv_i2c">
              <Attributes dnOrder="0">
                <String dnOrder="0" id="targetComponentID">
                  <Value dnOrder="0">gfx_maxtouch_controller</Value>
                </String>
                <String dnOrder="1" id="targetAttachmentID">
                  <Value dnOrder="0">i2c</Value>
                </String>
              </Attributes>
            </DirectCapability>
            <DirectDependency dnOrder="1" id="drv_i2c_I2C_dependency">
              <Attributes dnOrder="0">
                <String dnOrder="0" id="targetComponentID">
                  <Value dnOrder="0">i2c1</Value>
                </String>
                <String dnOrder="1" id="targetAttachmentID">
                  <Value dnOrder="0">I2C1_I2C</Value>
                </String>
              </Attributes>
            </DirectDependency>
          </Attachments>
        </InstanceComponent>
      </Instances>
    </GeneratorComponent>
    <GeneratorComponent dnOrder="7" id="drv_spi">
      <Symbols dnOrder="0">
        <Combo dnOrder="0" id="DRV_SPI_COMMON_MODE">
          <Values dnOrder="0">
            <Dynamic dnOrder="0" id="drv_spi" value="Asynchronous"/>
          </Values>
        </Combo>
      </Symbols>
      <Instances dnOrder="1">
        <InstanceComponent dnOrder="0" id="drv_spi" instance="0">
          <Symbols dnOrder="0">
            <Comment dnOrder="0" id="DRV_SPI_DEPENDENCY_DMA_COMMENT">
              <Attributes dnOrder="0">
                <Boolean dnOrder="0" id="visible">
                  <Value dnOrder="0">false</Value>
                </Boolean>
              </Attributes>
            </Comment>
            <String dnOrder="1" id="DRV_SPI_MODE">
              <Values dnOrder="0">
                <Dynamic dnOrder="0" id="drv_spi_0" value="Asynchronous"/>
              </Values>
            </String>
            <String dnOrder="2" id="DRV_SPI_PLIB">
              <Values dnOrder="0">
                <Dynamic dnOrder="0" id="drv_spi_0" value="SPI3"/>
              </Values>
            </String>
            <Integer dnOrder="3" id="DRV_SPI_RX_DMA_CHANNEL">
              <Values dnOrder="0">
                <Dynamic dnOrder="0" id="drv_spi_0" value="-1"/>
              </Values>
            </Integer>
            <Integer dnOrder="4" id="DRV_SPI_TX_DMA_CHANNEL">
              <Values dnOrder="0">
                <Dynamic dnOrder="0" id="drv_spi_0" value="-1"/>
              </Values>
            </Integer>
            <Boolean dnOrder="5" id="DRV_SPI_TX_RX_DMA">
              <Attributes dnOrder="0">
                <Boolean dnOrder="0" id="readOnly">
                  <Value dnOrder="0">false</Value>
                </Boolean>
              </Attributes>
            </Boolean>
          </Symbols>
          <Attachments dnOrder="1">
            <DirectCapability dnOrder="0" id="drv_spi">
              <Attributes dnOrder="0">
                <String dnOrder="0" id="targetComponentID">
                  <Value dnOrder="0">gfx_intf_spi4</Value>
                </String>
                <String dnOrder="1" id="targetAttachmentID">
                  <Value dnOrder="0">DRV_SPI</Value>
                </String>
              </Attributes>
            </DirectCapability>
            <DirectDependency dnOrder="1" id="drv_spi_SPI_dependency">
              <Attributes dnOrder="0">
                <String dnOrder="0" id="targetComponentID">
                  <Value dnOrder="0">spi3</Value>
                </String>
                <String dnOrder="1" id="targetAttachmentID">
                  <Value dnOrder="0">SPI3_SPI</Value>
                </String>
              </Attributes>
            </DirectDependency>
          </Attachments>
        </InstanceComponent>
      </Instances>
    </GeneratorComponent>
    <UniqueComponent dnOrder="8" id="gfx_disp_mxt_cpro_320x480">
      <Attachments dnOrder="0">
        <DirectCapability dnOrder="0" id="gfx_display">
          <Attributes dnOrder="0">
            <String dnOrder="0" id="targetComponentID">
              <Value dnOrder="0">gfx_hal</Value>
            </String>
            <String dnOrder="1" id="targetAttachmentID">
              <Value dnOrder="0">gfx_display</Value>
            </String>
          </Attributes>
        </DirectCapability>
        <DirectCapability dnOrder="1" id="touch_panel">
          <Attributes dnOrder="0">
            <String dnOrder="0" id="targetComponentID">
              <Value dnOrder="0">gfx_maxtouch_controller</Value>
            </String>
            <String dnOrder="1" id="targetAttachmentID">
              <Value dnOrder="0">touch_panel</Value>
            </String>
          </Attributes>
        </DirectCapability>
      </Attachments>
    </UniqueComponent>
    <UniqueComponent dnOrder="9" id="gfx_driver_ili9488">
      <Symbols dnOrder="0">
        <Integer dnOrder="0" id="DisplayHeight">
          <Attributes dnOrder="0">
            <Boolean dnOrder="0" id="visible">
              <Value dnOrder="0">false</Value>
            </Boolean>
          </Attributes>
        </Integer>
        <String dnOrder="1" id="DisplayInterface">
          <Values dnOrder="0">
            <Dynamic dnOrder="0" id="gfx_driver_ili9488" value="gfx_intf_spi4"/>
          </Values>
        </String>
        <String dnOrder="2" id="DisplayInterfaceType">
          <Values dnOrder="0">
            <Dynamic dnOrder="0" id="gfx_driver_ili9488" value="SPI 4-line"/>
          </Values>
        </String>
        <Integer dnOrder="3" id="DisplayWidth">
          <Attributes dnOrder="0">
            <Boolean dnOrder="0" id="visible">
              <Value dnOrder="0">false</Value>
            </Boolean>
          </Attributes>
        </Integer>
        <Boolean dnOrder="4" id="DrawBufferPreRead">
          <Attributes dnOrder="0">
            <Boolean dnOrder="0" id="visible">
              <Value dnOrder="0">false</Value>
            </Boolean>
          </Attributes>
        </Boolean>
        <Combo dnOrder="5" id="DrawBufferSize">
          <Values dnOrder="0">
            <Dynamic dnOrder="0" id="aria_gfx_xplained_pro" value="Pixel"/>
          </Values>
        </Combo>
        <File dnOrder="6" id="GFX_ILI9488_SPI">
          <Attributes dnOrder="0">
            <Boolean dnOrder="0" id="enabled">
              <Value dnOrder="0">true</Value>
            </Boolean>
          </Attributes>
        </File>
        <Comment dnOrder="7" id="HALComment">
          <Attributes dnOrder="0">
            <Boolean dnOrder="0" id="visible">
              <Value dnOrder="0">true</Value>
            </Boolean>
          </Attributes>
        </Comment>
        <Boolean dnOrder="8" id="HALConnected">
          <Values dnOrder="0">
            <Dynamic dnOrder="0" id="gfx_hal" value="true"/>
          </Values>
        </Boolean>
      </Symbols>
      <Attachments dnOrder="1">
        <DirectDependency dnOrder="0" id="Display Interface">
          <Attributes dnOrder="0">
            <String dnOrder="0" id="targetComponentID">
              <Value dnOrder="0">gfx_intf_spi4</Value>
            </String>
            <String dnOrder="1" id="targetAttachmentID">
              <Value dnOrder="0">gfx_intf_spi4</Value>
            </String>
          </Attributes>
        </DirectDependency>
        <DirectCapability dnOrder="1" id="gfx_driver_ili9488">
          <Attributes dnOrder="0">
            <String dnOrder="0" id="targetComponentID">
              <Value dnOrder="0">gfx_hal</Value>
            </String>
            <String dnOrder="1" id="targetAttachmentID">
              <Value dnOrder="0">gfx_display_driver</Value>
            </String>
          </Attributes>
        </DirectCapability>
      </Attachments>
    </UniqueComponent>
    <UniqueComponent dnOrder="10" id="gfx_hal">
      <Symbols dnOrder="0">
        <Boolean dnOrder="0" id="DisableGlobalPaletteModeHint">
          <Values dnOrder="0">
            <Dynamic dnOrder="0" id="aria_gfx_library" value="true"/>
          </Values>
        </Boolean>
        <Integer dnOrder="1" id="DisplayBacklightDisable">
          <Values dnOrder="0">
            <Dynamic dnOrder="0" id="gfx_hal" value="1"/>
          </Values>
        </Integer>
        <Integer dnOrder="2" id="DisplayBacklightEnable">
          <Values dnOrder="0">
            <Dynamic dnOrder="0" id="gfx_hal" value="1"/>
          </Values>
        </Integer>
        <Boolean dnOrder="3" id="DisplayChipSelectPolarity">
          <Values dnOrder="0">
            <Dynamic dnOrder="0" id="gfx_hal" value="true"/>
          </Values>
        </Boolean>
        <Boolean dnOrder="4" id="DisplayDataEnable">
          <Values dnOrder="0">
            <Dynamic dnOrder="0" id="gfx_hal" value="true"/>
          </Values>
        </Boolean>
        <Boolean dnOrder="5" id="DisplayDataEnablePolarity">
          <Values dnOrder="0">
            <Dynamic dnOrder="0" id="gfx_hal" value="true"/>
          </Values>
        </Boolean>
        <Integer dnOrder="6" id="DisplayDataWidth">
          <Values dnOrder="0">
            <Dynamic dnOrder="0" id="gfx_hal" value="16"/>
          </Values>
        </Integer>
        <Boolean dnOrder="7" id="DisplayHSYNCNegative">
          <Values dnOrder="0">
            <Dynamic dnOrder="0" id="gfx_hal" value="false"/>
          </Values>
        </Boolean>
        <Integer dnOrder="8" id="DisplayHeight">
          <Values dnOrder="0">
            <Dynamic dnOrder="0" id="gfx_hal" value="480"/>
          </Values>
        </Integer>
        <Integer dnOrder="9" id="DisplayHorzBackPorch">
          <Values dnOrder="0">
            <Dynamic dnOrder="0" id="gfx_hal" value="2"/>
          </Values>
        </Integer>
        <Integer dnOrder="10" id="DisplayHorzFrontPorch">
          <Values dnOrder="0">
            <Dynamic dnOrder="0" id="gfx_hal" value="2"/>
          </Values>
        </Integer>
        <Integer dnOrder="11" id="DisplayHorzPulseWidth">
          <Values dnOrder="0">
            <Dynamic dnOrder="0" id="gfx_hal" value="41"/>
          </Values>
        </Integer>
        <Boolean dnOrder="12" id="DisplayInvLeftShift">
          <Values dnOrder="0">
            <Dynamic dnOrder="0" id="gfx_hal" value="false"/>
          </Values>
        </Boolean>
        <String dnOrder="13" id="DisplayName">
          <Values dnOrder="0">
            <Dynamic dnOrder="0" id="gfx_hal" value="MXT-CPRO"/>
          </Values>
        </String>
        <Boolean dnOrder="14" id="DisplayResetPolarity">
          <Values dnOrder="0">
            <Dynamic dnOrder="0" id="gfx_hal" value="true"/>
          </Values>
        </Boolean>
        <Boolean dnOrder="15" id="DisplayUseChipSelect">
          <Values dnOrder="0">
            <Dynamic dnOrder="0" id="gfx_hal" value="false"/>
          </Values>
        </Boolean>
        <Boolean dnOrder="16" id="DisplayUseReset">
          <Values dnOrder="0">
            <Dynamic dnOrder="0" id="gfx_hal" value="true"/>
          </Values>
        </Boolean>
        <Boolean dnOrder="17" id="DisplayVSYNCNegative">
          <Values dnOrder="0">
            <Dynamic dnOrder="0" id="gfx_hal" value="false"/>
          </Values>
        </Boolean>
        <Integer dnOrder="18" id="DisplayVertBackPorch">
          <Values dnOrder="0">
            <Dynamic dnOrder="0" id="gfx_hal" value="2"/>
          </Values>
        </Integer>
        <Integer dnOrder="19" id="DisplayVertFrontPorch">
          <Values dnOrder="0">
            <Dynamic dnOrder="0" id="gfx_hal" value="2"/>
          </Values>
        </Integer>
        <Integer dnOrder="20" id="DisplayVertPulseWidth">
          <Values dnOrder="0">
            <Dynamic dnOrder="0" id="gfx_hal" value="10"/>
          </Values>
        </Integer>
        <Integer dnOrder="21" id="DisplayWidth">
          <Values dnOrder="0">
            <Dynamic dnOrder="0" id="gfx_hal" value="320"/>
          </Values>
        </Integer>
        <String dnOrder="22" id="DriverInfoFunction">
          <Values dnOrder="0">
            <Dynamic dnOrder="0" id="gfx_hal" value="driverILI9488InfoGet"/>
          </Values>
        </String>
        <String dnOrder="23" id="DriverInitFunction">
          <Values dnOrder="0">
            <Dynamic dnOrder="0" id="gfx_hal" value="driverILI9488ContextInitialize"/>
          </Values>
        </String>
        <Boolean dnOrder="24" id="GlobalPaletteModeHint">
          <Values dnOrder="0">
            <Dynamic dnOrder="0" id="aria_gfx_library" value="false"/>
          </Values>
        </Boolean>
        <Integer dnOrder="25" id="PixelClock">
          <Values dnOrder="0">
            <Dynamic dnOrder="0" id="gfx_hal" value="50000000"/>
          </Values>
        </Integer>
        <Integer dnOrder="26" id="RefreshRate">
          <Values dnOrder="0">
            <Dynamic dnOrder="0" id="gfx_hal" value="277"/>
          </Values>
        </Integer>
      </Symbols>
      <Attachments dnOrder="1">
        <DirectDependency dnOrder="0" id="gfx_display">
          <Attributes dnOrder="0">
            <String dnOrder="0" id="targetComponentID">
              <Value dnOrder="0">gfx_disp_mxt_cpro_320x480</Value>
            </String>
            <String dnOrder="1" id="targetAttachmentID">
              <Value dnOrder="0">gfx_display</Value>
            </String>
          </Attributes>
        </DirectDependency>
        <DirectDependency dnOrder="1" id="gfx_display_driver">
          <Attributes dnOrder="0">
            <String dnOrder="0" id="targetComponentID">
              <Value dnOrder="0">gfx_driver_ili9488</Value>
            </String>
            <String dnOrder="1" id="targetAttachmentID">
              <Value dnOrder="0">gfx_driver_ili9488</Value>
            </String>
          </Attributes>
        </DirectDependency>
        <DirectCapability dnOrder="2" id="gfx_hal">
          <Attributes dnOrder="0">
            <String dnOrder="0" id="targetComponentID">
              <Value dnOrder="0">aria_gfx_library</Value>
            </String>
            <String dnOrder="1" id="targetAttachmentID">
              <Value dnOrder="0">gfx_hal</Value>
            </String>
          </Attributes>
        </DirectCapability>
      </Attachments>
    </UniqueComponent>
    <UniqueComponent dnOrder="11" id="gfx_intf_spi4">
      <Attachments dnOrder="0">
        <DirectDependency dnOrder="0" id="DRV_SPI">
          <Attributes dnOrder="0">
            <String dnOrder="0" id="targetComponentID">
              <Value dnOrder="0">drv_spi_0</Value>
            </String>
            <String dnOrder="1" id="targetAttachmentID">
              <Value dnOrder="0">drv_spi</Value>
            </String>
          </Attributes>
        </DirectDependency>
        <DirectCapability dnOrder="1" id="gfx_intf_spi4">
          <Attributes dnOrder="0">
            <String dnOrder="0" id="targetComponentID">
              <Value dnOrder="0">gfx_driver_ili9488</Value>
            </String>
            <String dnOrder="1" id="targetAttachmentID">
              <Value dnOrder="0">Display&amp;#160;Interface</Value>
            </String>
          </Attributes>
        </DirectCapability>
      </Attachments>
    </UniqueComponent>
    <UniqueComponent dnOrder="12" id="gfx_maxtouch_controller">
      <Symbols dnOrder="0">
        <Combo dnOrder="0" id="DRV_I2C_MODE">
          <Values dnOrder="0">
            <Dynamic dnOrder="0" id="gfx_maxtouch_controller" value="Asynchronous"/>
          </Values>
        </Combo>
        <Integer dnOrder="1" id="DRV_MAXTOUCH_I2C_INDEX">
          <Attributes dnOrder="0">
            <Boolean dnOrder="0" id="readOnly">
              <Value dnOrder="0">true</Value>
            </Boolean>
          </Attributes>
          <Values dnOrder="1">
            <Dynamic dnOrder="0" id="gfx_maxtouch_controller" value="0"/>
          </Values>
        </Integer>
        <Integer dnOrder="2" id="Height">
          <Values dnOrder="0">
            <Dynamic dnOrder="0" id="gfx_maxtouch_controller" value="320"/>
          </Values>
        </Integer>
        <Boolean dnOrder="3" id="RTOSEnabled">
          <Attributes dnOrder="0">
            <Boolean dnOrder="0" id="enabled">
              <Value dnOrder="0">false</Value>
            </Boolean>
          </Attributes>
        </Boolean>
        <Menu dnOrder="4" id="RTOSMenu">
          <Attributes dnOrder="0">
            <Boolean dnOrder="0" id="visible">
              <Value dnOrder="0">false</Value>
            </Boolean>
          </Attributes>
        </Menu>
        <File dnOrder="5" id="TOUCH_DRV_RTOS_TASK_C">
          <Attributes dnOrder="0">
            <Boolean dnOrder="0" id="enabled">
              <Value dnOrder="0">false</Value>
            </Boolean>
          </Attributes>
        </File>
        <Integer dnOrder="6" id="Width">
          <Values dnOrder="0">
            <Dynamic dnOrder="0" id="gfx_maxtouch_controller" value="480"/>
          </Values>
        </Integer>
      </Symbols>
      <Attachments dnOrder="1">
        <DirectDependency dnOrder="0" id="i2c">
          <Attributes dnOrder="0">
            <String dnOrder="0" id="targetComponentID">
              <Value dnOrder="0">drv_i2c_0</Value>
            </String>
            <String dnOrder="1" id="targetAttachmentID">
              <Value dnOrder="0">drv_i2c</Value>
            </String>
          </Attributes>
        </DirectDependency>
        <DirectDependency dnOrder="1" id="touch_panel">
          <Attributes dnOrder="0">
            <String dnOrder="0" id="targetComponentID">
              <Value dnOrder="0">gfx_disp_mxt_cpro_320x480</Value>
            </String>
            <String dnOrder="1" id="targetAttachmentID">
              <Value dnOrder="0">touch_panel</Value>
            </String>
          </Attributes>
        </DirectDependency>
      </Attachments>
    </UniqueComponent>
    <UniqueComponent dnOrder="13" id="HarmonyCore">
      <Symbols dnOrder="0">
        <File dnOrder="0" id="APP0_C">
          <Attributes dnOrder="0">
            <Boolean dnOrder="0" id="enabled">
              <Value dnOrder="0">true</Value>
            </Boolean>
          </Attributes>
        </File>
        <File dnOrder="1" id="APP0_H">
          <Attributes dnOrder="0">
            <Boolean dnOrder="0" id="enabled">
              <Value dnOrder="0">true</Value>
            </Boolean>
          </Attributes>
        </File>
        <File dnOrder="2" id="CONFIGURATION_H">
          <Attributes dnOrder="0">
            <Boolean dnOrder="0" id="enabled">
              <Value dnOrder="0">true</Value>
            </Boolean>
          </Attributes>
        </File>
        <File dnOrder="3" id="DMA_DEF">
          <Attributes dnOrder="0">
            <Boolean dnOrder="0" id="enabled">
              <Value dnOrder="0">true</Value>
            </Boolean>
          </Attributes>
        </File>
        <File dnOrder="4" id="DMA_HEADER">
          <Attributes dnOrder="0">
            <Boolean dnOrder="0" id="enabled">
              <Value dnOrder="0">true</Value>
            </Boolean>
          </Attributes>
        </File>
        <File dnOrder="5" id="DMA_MAPPING">
          <Attributes dnOrder="0">
            <Boolean dnOrder="0" id="enabled">
              <Value dnOrder="0">true</Value>
            </Boolean>
          </Attributes>
        </File>
        <File dnOrder="6" id="DMA_SOURCE">
          <Attributes dnOrder="0">
            <Boolean dnOrder="0" id="enabled">
              <Value dnOrder="0">true</Value>
            </Boolean>
          </Attributes>
        </File>
        <File dnOrder="7" id="DRIVER_COMMON">
          <Attributes dnOrder="0">
            <Boolean dnOrder="0" id="enabled">
              <Value dnOrder="0">true</Value>
            </Boolean>
          </Attributes>
        </File>
        <File dnOrder="8" id="DRIVER_ROOT">
          <Attributes dnOrder="0">
            <Boolean dnOrder="0" id="enabled">
              <Value dnOrder="0">true</Value>
            </Boolean>
          </Attributes>
        </File>
        <Boolean dnOrder="9" id="ENABLE_APP_FILE">
          <Values dnOrder="0">
            <Dynamic dnOrder="0" id="HarmonyCore" value="true"/>
          </Values>
        </Boolean>
        <Boolean dnOrder="10" id="ENABLE_DRV_COMMON">
          <Values dnOrder="0">
            <Dynamic dnOrder="0" id="drv_spi_0" value="true"/>
          </Values>
        </Boolean>
        <Boolean dnOrder="11" id="ENABLE_OSAL">
          <Values dnOrder="0">
            <Dynamic dnOrder="0" id="HarmonyCore" value="true"/>
          </Values>
        </Boolean>
        <Boolean dnOrder="12" id="ENABLE_SYS_CACHE">
          <Values dnOrder="0">
            <Dynamic dnOrder="0" id="HarmonyCore" value="false"/>
          </Values>
        </Boolean>
        <Boolean dnOrder="13" id="ENABLE_SYS_COMMON">
          <Values dnOrder="0">
            <Dynamic dnOrder="0" id="drv_spi_0" value="true"/>
          </Values>
        </Boolean>
        <Boolean dnOrder="14" id="ENABLE_SYS_DMA">
          <Values dnOrder="0">
            <Dynamic dnOrder="0" id="drv_spi_0" value="true"/>
          </Values>
        </Boolean>
        <Boolean dnOrder="15" id="ENABLE_SYS_INT">
          <Values dnOrder="0">
            <Dynamic dnOrder="0" id="HarmonyCore" value="true"/>
          </Values>
        </Boolean>
        <Boolean dnOrder="16" id="ENABLE_SYS_PORTS">
          <Values dnOrder="0">
            <Dynamic dnOrder="0" id="drv_spi_0" value="true"/>
          </Values>
        </Boolean>
        <Menu dnOrder="17" id="GEN_APP_TASK_MENU">
          <Attributes dnOrder="0">
            <Boolean dnOrder="0" id="visible">
              <Value dnOrder="0">true</Value>
            </Boolean>
          </Attributes>
        </Menu>
        <File dnOrder="18" id="INT_DEF">
          <Attributes dnOrder="0">
            <Boolean dnOrder="0" id="enabled">
              <Value dnOrder="0">true</Value>
            </Boolean>
          </Attributes>
        </File>
        <File dnOrder="19" id="INT_HEADER">
          <Attributes dnOrder="0">
            <Boolean dnOrder="0" id="enabled">
              <Value dnOrder="0">true</Value>
            </Boolean>
          </Attributes>
        </File>
        <File dnOrder="20" id="INT_MAPPING">
          <Attributes dnOrder="0">
            <Boolean dnOrder="0" id="enabled">
              <Value dnOrder="0">true</Value>
            </Boolean>
          </Attributes>
        </File>
        <File dnOrder="21" id="INT_SOURCE">
          <Attributes dnOrder="0">
            <Boolean dnOrder="0" id="enabled">
              <Value dnOrder="0">true</Value>
            </Boolean>
          </Attributes>
        </File>
        <File dnOrder="22" id="OSAL_DEFINITIONS_H">
          <Attributes dnOrder="0">
            <Boolean dnOrder="0" id="enabled">
              <Value dnOrder="0">true</Value>
            </Boolean>
          </Attributes>
        </File>
        <File dnOrder="23" id="OSAL_H">
          <Attributes dnOrder="0">
            <Boolean dnOrder="0" id="enabled">
              <Value dnOrder="0">true</Value>
            </Boolean>
          </Attributes>
        </File>
        <File dnOrder="24" id="OSAL_IMPL_BASIC_H">
          <Attributes dnOrder="0">
            <Boolean dnOrder="0" id="enabled">
              <Value dnOrder="0">true</Value>
            </Boolean>
          </Attributes>
        </File>
        <File dnOrder="25" id="OSAL_SYSDEF_H">
          <Attributes dnOrder="0">
            <Boolean dnOrder="0" id="enabled">
              <Value dnOrder="0">true</Value>
            </Boolean>
          </Attributes>
        </File>
        <File dnOrder="26" id="PORTS_DEF">
          <Attributes dnOrder="0">
            <Boolean dnOrder="0" id="enabled">
              <Value dnOrder="0">true</Value>
            </Boolean>
          </Attributes>
        </File>
        <File dnOrder="27" id="PORTS_HEADER">
          <Attributes dnOrder="0">
            <Boolean dnOrder="0" id="enabled">
              <Value dnOrder="0">true</Value>
            </Boolean>
          </Attributes>
        </File>
        <File dnOrder="28" id="PORTS_MAPPING">
          <Attributes dnOrder="0">
            <Boolean dnOrder="0" id="enabled">
              <Value dnOrder="0">true</Value>
            </Boolean>
          </Attributes>
        </File>
        <Combo dnOrder="29" id="SELECT_RTOS">
          <Values dnOrder="0">
            <Dynamic dnOrder="0" id="HarmonyCore" value="BareMetal"/>
          </Values>
        </Combo>
        <File dnOrder="30" id="SYSTEM_COMMON">
          <Attributes dnOrder="0">
            <Boolean dnOrder="0" id="enabled">
              <Value dnOrder="0">true</Value>
            </Boolean>
          </Attributes>
        </File>
        <File dnOrder="31" id="SYSTEM_MODULE">
          <Attributes dnOrder="0">
            <Boolean dnOrder="0" id="enabled">
              <Value dnOrder="0">true</Value>
            </Boolean>
          </Attributes>
        </File>
        <File dnOrder="32" id="SYSTEM_ROOT">
          <Attributes dnOrder="0">
            <Boolean dnOrder="0" id="enabled">
              <Value dnOrder="0">true</Value>
            </Boolean>
          </Attributes>
        </File>
        <File dnOrder="33" id="TASKS_C">
          <Attributes dnOrder="0">
            <Boolean dnOrder="0" id="enabled">
              <Value dnOrder="0">true</Value>
            </Boolean>
          </Attributes>
        </File>
        <File dnOrder="34" id="USER_H">
          <Attributes dnOrder="0">
            <Boolean dnOrder="0" id="enabled">
              <Value dnOrder="0">true</Value>
            </Boolean>
          </Attributes>
        </File>
      </Symbols>
    </UniqueComponent>
    <UniqueComponent dnOrder="14" id="i2c1">
      <Symbols dnOrder="0">
        <Integer dnOrder="0" id="BRG_VALUE">
          <Values dnOrder="0">
            <Dynamic dnOrder="0" id="i2c1" value="4992"/>
          </Values>
        </Integer>
        <Integer dnOrder="1" id="I2C_CLOCK_FREQ">
          <Values dnOrder="0">
            <Dynamic dnOrder="0" id="i2c1" value="100000000"/>
          </Values>
        </Integer>
        <Long dnOrder="2" id="I2C_CLOCK_SPEED">
          <Values dnOrder="0">
            <User dnOrder="0" value="10000"/>
          </Values>
        </Long>
      </Symbols>
      <Attachments dnOrder="1">
        <DirectCapability dnOrder="0" id="I2C1_I2C">
          <Attributes dnOrder="0">
            <String dnOrder="0" id="targetComponentID">
              <Value dnOrder="0">drv_i2c_0</Value>
            </String>
            <String dnOrder="1" id="targetAttachmentID">
              <Value dnOrder="0">drv_i2c_I2C_dependency</Value>
            </String>
          </Attributes>
        </DirectCapability>
      </Attachments>
    </UniqueComponent>
    <UniqueComponent dnOrder="15" id="spi3">
      <Symbols dnOrder="0">
        <Integer dnOrder="0" id="SPI_BAUD_RATE">
          <Values dnOrder="0">
            <Dynamic dnOrder="0" id="aria_gfx_xplained_pro" value="35000000"/>
          </Values>
        </Integer>
        <Integer dnOrder="1" id="SPI_BRG_VALUE">
          <Values dnOrder="0">
            <Dynamic dnOrder="0" id="spi3" value="1"/>
          </Values>
        </Integer>
      </Symbols>
      <Attachments dnOrder="1">
        <DirectCapability dnOrder="0" id="SPI3_SPI">
          <Attributes dnOrder="0">
            <String dnOrder="0" id="targetComponentID">
              <Value dnOrder="0">drv_spi_0</Value>
            </String>
            <String dnOrder="1" id="targetAttachmentID">
              <Value dnOrder="0">drv_spi_SPI_dependency</Value>
            </String>
          </Attributes>
        </DirectCapability>
      </Attachments>
    </UniqueComponent>
    <UniqueComponent dnOrder="16" id="sys_input">
      <Symbols dnOrder="0">
        <Boolean dnOrder="0" id="RTOSEnabled">
          <Values dnOrder="0">
            <Dynamic dnOrder="0" id="sys_input" value="false"/>
          </Values>
        </Boolean>
      </Symbols>
    </UniqueComponent>
    <UniqueComponent dnOrder="17" id="sys_time">
      <Symbols dnOrder="0">
        <Combo dnOrder="0" id="SYS_TIME_OPERATING_MODE">
          <Values dnOrder="0">
            <Dynamic dnOrder="0" id="sys_time" value="TICKLESS"/>
          </Values>
        </Combo>
        <String dnOrder="1" id="SYS_TIME_PLIB">
          <Values dnOrder="0">
            <Dynamic dnOrder="0" id="sys_time" value="CORE_TIMER"/>
          </Values>
        </String>
        <String dnOrder="2" id="SYS_TIME_REMOTE_COMPONENT_ID">
          <Values dnOrder="0">
            <Dynamic dnOrder="0" id="sys_time" value="core_timer"/>
          </Values>
        </String>
      </Symbols>
      <Attachments dnOrder="1">
        <DirectDependency dnOrder="0" id="sys_time_TMR_dependency">
          <Attributes dnOrder="0">
            <String dnOrder="0" id="targetComponentID">
              <Value dnOrder="0">core_timer</Value>
            </String>
            <String dnOrder="1" id="targetAttachmentID">
              <Value dnOrder="0">CORE_TIMER_TMR</Value>
            </String>
          </Attributes>
        </DirectDependency>
      </Attachments>
    </UniqueComponent>
  </Components>
  <UserData>
    <ComponentGraph dnOrder="0" id="__ROOTVIEW">
      <ElementPositions dnOrder="0">
        <ElementPosition dnOrder="0" id="BSP_PIC32MZ_EF_Curiosity_2.0" x="340" y="20"/>
        <ElementPosition dnOrder="1" id="HarmonyCore" x="585" y="33"/>
        <ElementPosition dnOrder="2" id="aria_gfx_library" x="830" y="175"/>
        <ElementPosition dnOrder="3" id="aria_gfx_xplained_pro" x="294" y="56"/>
        <ElementPosition dnOrder="4" id="core" x="240" y="20"/>
        <ElementPosition dnOrder="5" id="core_timer" x="11" y="61"/>
        <ElementPosition dnOrder="6" id="dfp" x="20" y="20"/>
        <ElementPosition dnOrder="7" id="drv_i2c" x="380" y="352"/>
        <ElementPosition dnOrder="8" id="drv_spi" x="140" y="218"/>
        <ElementPosition dnOrder="9" id="gfx_disp_mxt_cpro_320x480" x="282" y="101"/>
        <ElementPosition dnOrder="10" id="gfx_driver_ili9488" x="469" y="222"/>
        <ElementPosition dnOrder="11" id="gfx_hal" x="634" y="174"/>
        <ElementPosition dnOrder="12" id="gfx_intf_spi4" x="284" y="194"/>
        <ElementPosition dnOrder="13" id="gfx_maxtouch_controller" x="650" y="326"/>
        <ElementPosition dnOrder="14" id="i2c1" x="151" y="414"/>
        <ElementPosition dnOrder="15" id="spi3" x="7" y="226"/>
        <ElementPosition dnOrder="16" id="sys_input" x="760" y="20"/>
        <ElementPosition dnOrder="17" id="sys_time" x="147" y="58"/>
      </ElementPositions>
    </ComponentGraph>
    <GraphSettings canvasHeight="400" canvasWidth="400" dnOrder="1"/>
  </UserData>
</Configuration>
